erpbrasil.base-2.4.0-py3.10-nspkg.pth
erpbrasil/base/__init__.py
erpbrasil/base/__main__.py
erpbrasil/base/cli.py
erpbrasil/base/misc.py
erpbrasil/base/fiscal/__init__.py
erpbrasil/base/fiscal/bacen.py
erpbrasil/base/fiscal/cnpj_cpf.py
erpbrasil/base/fiscal/codigo_municipio.py
erpbrasil/base/fiscal/edoc.py
erpbrasil/base/fiscal/ie.py
erpbrasil/base/fiscal/pis.py
erpbrasil/base/fiscal/recopi.py
erpbrasil/base/fiscal/suframa.py
erpbrasil/base/gs1/__init__.py
erpbrasil/base/gs1/gsin.py
erpbrasil/base/gs1/gtin.py
erpbrasil/base/gs1/sscc.py
erpbrasil_base-2.4.0.dist-info/licenses/LICENSE
erpbrasil_base-2.4.0.dist-info/METADATA
erpbrasil_base-2.4.0.dist-info/WHEEL
erpbrasil_base-2.4.0.dist-info/entry_points.txt
erpbrasil_base-2.4.0.dist-info/namespace_packages.txt
erpbrasil_base-2.4.0.dist-info/top_level.txt
erpbrasil_base-2.4.0.dist-info/RECORD
