Metadata-Version: 2.4
Name: erpbrasil.base
Version: 2.4.0
Summary: Base
Home-page: https://github.com/erpbrasil/erpbrasil.base
Author: Luis Felipe Mileo
Author-email: mileo@kmee.com.br
License: MIT license
Project-URL: Documentation, https://erpbrasilbase.readthedocs.io/
Project-URL: Changelog, https://erpbrasilbase.readthedocs.io/en/latest/changelog.html
Project-URL: Issue Tracker, https://github.com/erpbrasil/erpbrasil.base/issues
Classifier: Development Status :: 5 - Production/Stable
Classifier: Intended Audience :: Developers
Classifier: License :: OSI Approved :: MIT License
Classifier: Operating System :: Unix
Classifier: Operating System :: POSIX
Classifier: Operating System :: Microsoft :: Windows
Classifier: Programming Language :: Python
Classifier: Programming Language :: Python :: 2.7
Classifier: Programming Language :: Python :: 3
Classifier: Programming Language :: Python :: 3.4
Classifier: Programming Language :: Python :: 3.5
Classifier: Programming Language :: Python :: 3.6
Classifier: Programming Language :: Python :: 3.7
Classifier: Programming Language :: Python :: Implementation :: CPython
Classifier: Programming Language :: Python :: Implementation :: PyPy
Classifier: Topic :: Utilities
Requires-Python: >=2.7, !=3.0.*, !=3.1.*, !=3.2.*, !=3.3.*
License-File: LICENSE
Dynamic: author
Dynamic: author-email
Dynamic: classifier
Dynamic: description
Dynamic: home-page
Dynamic: license
Dynamic: license-file
Dynamic: project-url
Dynamic: requires-python
Dynamic: summary
